pypbo/__init__.py
pypbo/pbo.py
pypbo/perf/__init__.py
pypbo/perf/metrics.py
rltrade_pypbo-0.0.3.dist-info/LICENSE
rltrade_pypbo-0.0.3.dist-info/METADATA
rltrade_pypbo-0.0.3.dist-info/WHEEL
rltrade_pypbo-0.0.3.dist-info/top_level.txt
rltrade_pypbo-0.0.3.dist-info/RECORD
